mmc/__init__.py
mmc/py.typed
mmc-0.1.2.dist-info/METADATA
mmc-0.1.2.dist-info/WHEEL
mmc-0.1.2.dist-info/licenses/LICENSE
mmc-0.1.2.dist-info/RECORD
